src/coeiroink/__init__.py
src/coeiroink/Synthesizer.py
src/sharevox/__init__.py
src/sharevox/Synthesizer.py
src/voicevox/__init__.py
src/voicevox/Synthesizer.py
voicevox_py-1.3.1.dist-info/METADATA
voicevox_py-1.3.1.dist-info/WHEEL
voicevox_py-1.3.1.dist-info/RECORD
