Metadata-Version: 2.1
Name: voicevox-py
Version: 1.3.1
Summary: Make VOICEVOX available on Python.
License: MIT
Author: sonyakun
Requires-Python: >=3.10,<4.0
Classifier: License :: OSI Approved :: MIT License
Classifier: Programming Language :: Python :: 3
Classifier: Programming Language :: Python :: 3.10
Classifier: Programming Language :: Python :: 3.11
Requires-Dist: httpx (>=0.24.1,<0.25.0)
